joiner.py
joiner_python-0.1.1.dist-info/LICENSE
joiner_python-0.1.1.dist-info/METADATA
joiner_python-0.1.1.dist-info/WHEEL
joiner_python-0.1.1.dist-info/top_level.txt
joiner_python-0.1.1.dist-info/RECORD
